dbs/__init__.py
dbs/exceptions.py
dbs/query.py
dbs/rows_transformation.py
dbs-0.1.5.dist-info/METADATA
dbs-0.1.5.dist-info/entry_points.txt
dbs-0.1.5.dist-info/WHEEL
dbs-0.1.5.dist-info/RECORD
