Metadata-Version: 2.1
Name: dbs
Version: 0.1.5
Summary: 
Author: yeger00
Author-email: yeger00@gmail.com
Requires-Python: >=3.10,<4.0
Classifier: Programming Language :: Python :: 3
Classifier: Programming Language :: Python :: 3.10
Classifier: Programming Language :: Python :: 3.11
Requires-Dist: databases[aiosqlite] (>=0.6.1,<0.7.0)
Requires-Dist: pydantic (>=1.10.4,<2.0.0)
Requires-Dist: rich (>=12.6.0,<13.0.0)
Requires-Dist: typer (>=0.6.1,<0.7.0)
